{
  "source": "bdns",
  "source_id": "898831",
  "source_lang": "es",
  "level": "local",
  "programme": "Concurrencia competitiva - canónica",
  "sub_programme": null,
  "publishing_authority_code": "LOCAL / ÁVILA / AYUNTAMIENTO DE ÁVILA",
  "nuts_codes": [
    "ES41"
  ],
  "nuts_primary": "ES41",
  "title": "Convocatoria de subvenciones para actividades culturales, animación y esparcimiento,",
  "title_lang": "es",
  "summary": "Cultura",
  "status": "open",
  "publication_date": "2026-04-14",
  "open_date": null,
  "deadline": null,
  "deadline_model": "continuous",
  "deadlines_extra": null,
  "budget_total_eur": 4000,
  "budget_per_project_min_eur": null,
  "budget_per_project_max_eur": null,
  "expected_grants": null,
  "cofinancing_pct": null,
  "duration_months": null,
  "audience": "PERSONAS JURÍDICAS QUE NO DESARROLLAN ACTIVIDAD ECONÓMICA",
  "eligible_orgs": [
    "PERSONAS JURÍDICAS QUE NO DESARROLLAN ACTIVIDAD ECONÓMICA"
  ],
  "eligible_countries": [
    "ES"
  ],
  "sectores": [
    {
      "codigo": "Q",
      "descripcion": "EDUCACIÓN"
    }
  ],
  "apply_url": "sede.avila.es",
  "details_url": "https://www.infosubvenciones.es/bdnstrans/GE/es/convocatoria/898831",
  "documents": [
    {
      "label": "III",
      "url": null
    },
    {
      "label": "VI",
      "url": null
    },
    {
      "label": "IV",
      "url": null
    },
    {
      "label": "II",
      "url": null
    },
    {
      "label": "VII",
      "url": null
    },
    {
      "label": "I",
      "url": null
    },
    {
      "label": "Documento de la convocatoria en español",
      "url": null
    }
  ],
  "bases_reguladoras_url": "wwwavila.es",
  "text_inicio": "Publicación BOP Ávila",
  "text_fin": "Veinte días naturales a contar desde el día siguiente a la publicación BOP",
  "se_publica_diario_oficial": true,
  "ayuda_estado": null,
  "fondos": [],
  "reglamento": null,
  "objetivos": [],
  "sectores_productos": [],
  "anuncios": [],
  "mrr_flag": false,
  "fetchedAt": "2026-05-07T12:06:46.709Z"
}