{
  "identifier": "EuropeAid/186204/DD/ACT/MW",
  "ccm2Id": "",
  "callIdentifier": "186204",
  "callTitle": "",
  "title": "Strengthening the capacity and voice of Civil Society Organizations as actors of accountability and transparency in Malawi",
  "programme": "NDICI / EuropeAid",
  "programmeCode": "111111",
  "programmePeriod": "2014 - 20202021 - 2027",
  "status": "open",
  "statusCode": "31094502",
  "opening": "2026-03-28",
  "deadline": "2026-05-29",
  "deadlineModel": "",
  "actionType": "",
  "actionCode": null,
  "mgaCode": null,
  "budget": null,
  "keywords": [],
  "crossCuttingPriorities": [],
  "supportInfoText": "",
  "submissionUrl": null,
  "topicUrl": "https://webgate.ec.europa.eu/prospect/external/publishedcalls.htm?callId=186204",
  "documents": [],
  "fetchedAt": "2026-05-07T12:03:27.598Z"
}