{
  "source": "bdns",
  "source_id": "899321",
  "source_lang": "es",
  "level": "local",
  "programme": "Concurrencia competitiva - canónica",
  "sub_programme": null,
  "publishing_authority_code": "LOCAL / DIPUTACIÓN PROV. DE SEGOVIA / DIPUTACIÓN PROVINCIAL DE SEGOVIA",
  "nuts_codes": [
    "ES416"
  ],
  "nuts_primary": "ES416",
  "title": "CONVOCATORIA PARA LA CONCESIÓN DE AYUDAS PARA EL COMERCIO RURAL MINORISTA Y VENTA AMBULANTE (2026)",
  "title_lang": "es",
  "summary": "Comercio, Turismo y Pymes",
  "status": "open",
  "publication_date": "2026-04-16",
  "open_date": "2026-04-23",
  "deadline": "2026-05-22",
  "deadline_model": "single-stage",
  "deadlines_extra": null,
  "budget_total_eur": 220000,
  "budget_per_project_min_eur": null,
  "budget_per_project_max_eur": null,
  "expected_grants": null,
  "cofinancing_pct": null,
  "duration_months": null,
  "audience": "PYME Y PERSONAS FÍSICAS QUE DESARROLLAN ACTIVIDAD ECONÓMICA",
  "eligible_orgs": [
    "PYME Y PERSONAS FÍSICAS QUE DESARROLLAN ACTIVIDAD ECONÓMICA"
  ],
  "eligible_countries": [
    "ES"
  ],
  "sectores": [
    {
      "codigo": "G",
      "descripcion": "COMERCIO AL POR MAYOR Y AL POR MENOR"
    }
  ],
  "apply_url": "https://sede.dipsegovia.es/",
  "details_url": "https://www.infosubvenciones.es/bdnstrans/GE/es/convocatoria/899321",
  "documents": [
    {
      "label": "Documento de la convocatoria en español",
      "url": null
    }
  ],
  "bases_reguladoras_url": "https://www.dipsegovia.es/es/la-institucion/servicios/subvenciones-promocion-provincial",
  "text_inicio": null,
  "text_fin": null,
  "se_publica_diario_oficial": true,
  "ayuda_estado": null,
  "fondos": [],
  "reglamento": null,
  "objetivos": [],
  "sectores_productos": [],
  "anuncios": [],
  "mrr_flag": false,
  "fetchedAt": "2026-05-07T12:06:46.948Z"
}