{
  "source": "bdns",
  "source_id": "910077",
  "source_lang": "es",
  "level": "ccaa",
  "programme": "Concesión directa - canónica",
  "sub_programme": null,
  "publishing_authority_code": "AUTONOMICA / LA RIOJA / CONSEJERÍA DE POLÍTICA LOCAL, INFRAESTRUCTURAS Y LUCHA CONTRA LA DESPOBLACIÓN",
  "nuts_codes": [
    "ES230"
  ],
  "nuts_primary": "ES230",
  "title": "Subvención para redacción y elaboración de planeamiento urbanístico",
  "title_lang": "es",
  "summary": "Otras Prestaciones económicas",
  "status": "open",
  "publication_date": "2026-06-02",
  "open_date": null,
  "deadline": null,
  "deadline_model": "continuous",
  "deadlines_extra": null,
  "budget_total_eur": 100000,
  "budget_per_project_min_eur": null,
  "budget_per_project_max_eur": null,
  "expected_grants": null,
  "cofinancing_pct": null,
  "duration_months": null,
  "audience": "PERSONAS JURÍDICAS QUE NO DESARROLLAN ACTIVIDAD ECONÓMICA",
  "eligible_orgs": [
    "PERSONAS JURÍDICAS QUE NO DESARROLLAN ACTIVIDAD ECONÓMICA"
  ],
  "eligible_countries": [
    "ES"
  ],
  "sectores": [
    {
      "codigo": "71",
      "descripcion": "Servicios técnicos de arquitectura e ingeniería; ensayos y análisis técnicos"
    }
  ],
  "apply_url": null,
  "details_url": "https://www.infosubvenciones.es/bdnstrans/GE/es/convocatoria/910077",
  "documents": [
    {
      "label": "Texto en castellano de la convocatoria",
      "url": null
    }
  ],
  "bases_reguladoras_url": "https://web.larioja.org/normativa?n=3196",
  "text_inicio": "Desde el día siguiente al de la publicación en el BOR del extracto de la convocatoria",
  "text_fin": "4 meses desde el día siguiente a la publicación extracto convocatoria",
  "se_publica_diario_oficial": true,
  "ayuda_estado": null,
  "fondos": [],
  "reglamento": null,
  "objetivos": [],
  "sectores_productos": [],
  "anuncios": [],
  "mrr_flag": false,
  "fetchedAt": "2026-06-08T04:05:18.552Z"
}