{
  "source": "bdns",
  "source_id": "907262",
  "source_lang": "es",
  "level": "local",
  "programme": "Concurrencia competitiva - canónica",
  "sub_programme": null,
  "publishing_authority_code": "LOCAL / VILAFRANCA DEL PENEDÈS / AYUNTAMIENTO DE VILAFRANCA DEL PENEDÈS",
  "nuts_codes": [
    "ES511"
  ],
  "nuts_primary": "ES511",
  "title": "CONVOCATORIA PÚBLICA CONCESIÓN AYUDAS Y SUBVENCIONES, A LAS ENTIDADES PRIVADAS QUE EJECUTEN ACTIVIDADES EN EL ÁMBITO DE LA SALUD DE LAS PERSONAS, AÑO 2026",
  "title_lang": "es",
  "summary": "Sanidad",
  "status": "open",
  "publication_date": "2026-05-21",
  "open_date": null,
  "deadline": null,
  "deadline_model": "continuous",
  "deadlines_extra": null,
  "budget_total_eur": 25000,
  "budget_per_project_min_eur": null,
  "budget_per_project_max_eur": null,
  "expected_grants": null,
  "cofinancing_pct": null,
  "duration_months": null,
  "audience": "GRAN EMPRESA; PERSONAS FÍSICAS QUE NO DESARROLLAN ACTIVIDAD ECONÓMICA; PERSONAS JURÍDICAS QUE NO DESARROLLAN ACTIVIDAD ECONÓMICA; PYME Y PERSONAS FÍSICAS QUE DESARROLLAN ACTIVIDAD ECONÓMICA",
  "eligible_orgs": [
    "GRAN EMPRESA",
    "PERSONAS FÍSICAS QUE NO DESARROLLAN ACTIVIDAD ECONÓMICA",
    "PERSONAS JURÍDICAS QUE NO DESARROLLAN ACTIVIDAD ECONÓMICA",
    "PYME Y PERSONAS FÍSICAS QUE DESARROLLAN ACTIVIDAD ECONÓMICA"
  ],
  "eligible_countries": [
    "ES"
  ],
  "sectores": [
    {
      "codigo": "T",
      "descripcion": "OTROS SERVICIOS"
    }
  ],
  "apply_url": "https://seu.vilafranca.cat/",
  "details_url": "https://www.infosubvenciones.es/bdnstrans/GE/es/convocatoria/907262",
  "documents": [
    {
      "label": "Documento de la convocatoria en lengua cooficial",
      "url": null
    },
    {
      "label": "Documento de la convocatoria en español",
      "url": null
    }
  ],
  "bases_reguladoras_url": "https://seu.vilafranca.cat/",
  "text_inicio": "DIA SIGUIENTE A LA PUBLICACIÓN DE LA CONVOCATORIA EL BOPB",
  "text_fin": "30 DIAS NATURALES A PARTIR DE LA PUBLICACIÓN EN EL BOPB",
  "se_publica_diario_oficial": true,
  "ayuda_estado": null,
  "fondos": [],
  "reglamento": null,
  "objetivos": [],
  "sectores_productos": [],
  "anuncios": [],
  "mrr_flag": false,
  "fetchedAt": "2026-06-13T04:08:12.966Z"
}