{
  "identifier": "HORIZON-EIC-2023-ACCELERATORCHALLENGES-05",
  "ccm2Id": "45602336",
  "callIdentifier": "HORIZON-EIC-2023-ACCELERATOR-01",
  "callTitle": "",
  "title": "EIC Accelerator Challenge: Emerging semiconductor or quantum technology components",
  "programme": "Horizon Europe",
  "programmeCode": "43108390",
  "programmePeriod": "2021 - 2027",
  "status": "open",
  "statusCode": "31094502",
  "opening": "2022-12-08",
  "deadline": "2023-01-11",
  "deadlineModel": "multiple cut-off",
  "actionType": "HORIZON EIC Accelerator Blended Finance",
  "actionCode": null,
  "mgaCode": null,
  "budget": null,
  "keywords": [
    "[\"Digital Agenda\",\"Artificial Intelligence\"]"
  ],
  "crossCuttingPriorities": [
    "DigitalAgenda",
    "AI"
  ],
  "supportInfoText": "",
  "submissionUrl": null,
  "topicUrl": "https://ec.europa.eu/info/funding-tenders/opportunities/data/topicDetails/HORIZON-EIC-2023-ACCELERATORCHALLENGES-05.json",
  "documents": [],
  "fetchedAt": "2026-07-15T04:02:52.484Z"
}