{
  "identifier": "HORIZON-EIE-2024-CONNECT-01-02",
  "ccm2Id": "45659287",
  "callIdentifier": "HORIZON-EIE-2024-CONNECT-01",
  "callTitle": "",
  "title": "Startup Europe",
  "programme": "Horizon Europe",
  "programmeCode": "43108390",
  "programmePeriod": "2021 - 2027",
  "status": "forthcoming",
  "statusCode": "31094501",
  "opening": "2024-01-11",
  "deadline": "2024-04-25",
  "deadlineModel": "single-stage",
  "actionType": "HORIZON Coordination and Support Actions",
  "actionCode": null,
  "mgaCode": null,
  "budget": null,
  "keywords": [
    "[\"Knowledge transfer\",\"Innovation support services\",\"Technology transfer\",\"Industrial innovation policy\",\"Knowledge and Technology transfer\",\"Business strategies\",\"Gender in innovation development\",\"Technology commercialisation\",\"Entrepreneurship\",\"Innovation policy\",\"Business development\",\"Intercultural business communication\",\"Smart Specialisation strategies\",\"Regional development\",\"Technology development\",\"Business support services\",\"Project management and coordination\",\"Market development\",\"Innovation and diversity (e.g. gender)\",\"New business opportunities\",\"Market-creating innovation\",\"Innovation systems\",\"Incubator companies\",\"innovation ecosystems\",\"acceleration acitivities\",\"start-ups\",\"digital technologies\",\"cross-border\"]"
  ],
  "crossCuttingPriorities": [],
  "supportInfoText": "",
  "submissionUrl": null,
  "topicUrl": "https://ec.europa.eu/info/funding-tenders/opportunities/data/topicDetails/HORIZON-EIE-2024-CONNECT-01-02.json",
  "documents": [],
  "fetchedAt": "2026-07-05T04:04:39.747Z"
}