{
  "source": "bdns",
  "source_id": "903564",
  "source_lang": "es",
  "level": "otros",
  "programme": "Concurrencia competitiva - canónica",
  "sub_programme": null,
  "publishing_authority_code": "OTROS / CÁMARA DE COMERCIO DE JEREZ",
  "nuts_codes": [
    "ES612"
  ],
  "nuts_primary": "ES612",
  "title": "CONVOCATORIA PYME GLOBAL 2026- CÁMARA JEREZ",
  "title_lang": "es",
  "summary": "Otras actuaciones de carácter económico",
  "status": "open",
  "publication_date": "2026-05-05",
  "open_date": null,
  "deadline": "2026-06-01",
  "deadline_model": "continuous",
  "deadlines_extra": null,
  "budget_total_eur": 13294.75,
  "budget_per_project_min_eur": null,
  "budget_per_project_max_eur": null,
  "expected_grants": null,
  "cofinancing_pct": null,
  "duration_months": null,
  "audience": "PYME Y PERSONAS FÍSICAS QUE DESARROLLAN ACTIVIDAD ECONÓMICA",
  "eligible_orgs": [
    "PYME Y PERSONAS FÍSICAS QUE DESARROLLAN ACTIVIDAD ECONÓMICA"
  ],
  "eligible_countries": [
    "ES"
  ],
  "sectores": [
    {
      "codigo": "S",
      "descripcion": "ACTIVIDADES ARTÍSTICAS, DEPORTIVAS Y DE ENTRETENIMIENTO"
    },
    {
      "codigo": "G",
      "descripcion": "COMERCIO AL POR MAYOR Y AL POR MENOR"
    },
    {
      "codigo": "Q",
      "descripcion": "EDUCACIÓN"
    },
    {
      "codigo": "I",
      "descripcion": "HOSTELERÍA"
    }
  ],
  "apply_url": "https://sede.camara.es/sede/jerez",
  "details_url": "https://www.infosubvenciones.es/bdnstrans/GE/es/convocatoria/903564",
  "documents": [
    {
      "label": "Anexo II_Declaración responsable empresa Pyme Global",
      "url": null
    },
    {
      "label": "Anexo III_Modelo de Solicitud admisión segundo participante",
      "url": null
    },
    {
      "label": "Anexo I_Tipologia Gastos Elegibles y Justificación empresa beneficiaria",
      "url": null
    },
    {
      "label": "Documento de la convocatoria en español",
      "url": null
    }
  ],
  "bases_reguladoras_url": "https://camarajerez.es/mision-enoturismo-valle del rodano-2026",
  "text_inicio": "A las 9:00h desde el día hábil siguiente a la publicación en Boletín Oficial de la Provinci de Cádiz",
  "text_fin": "A las 14:00h o hasta agotar el presupuesto consignado en la convocatoria",
  "se_publica_diario_oficial": true,
  "ayuda_estado": null,
  "fondos": [
    {
      "descripcion": "FEDER - FONDO EUROPEO DE DESARROLLO REGIONAL"
    }
  ],
  "reglamento": {
    "descripcion": "REG (UE) 2023/2831 de minimis, General",
    "orden": null
  },
  "objetivos": [],
  "sectores_productos": [],
  "anuncios": [],
  "mrr_flag": false,
  "fetchedAt": "2026-05-07T12:06:49.193Z"
}