{
  "id": 1104787,
  "organo": {
    "nivel1": "AUTONOMICA",
    "nivel2": "PRINCIPADO DE ASTURIAS",
    "nivel3": "CONSEJERÍA DE PRESIDENCIA, RETO DEMOGRÁFICO, IGUALDAD Y TURISMO"
  },
  "sedeElectronica": null,
  "codigoBDNS": "903226",
  "fechaRecepcion": "2026-05-04",
  "instrumentos": [
    {
      "descripcion": "SUBVENCIÓN Y ENTREGA DINERARIA SIN CONTRAPRESTACIÓN "
    }
  ],
  "tipoConvocatoria": "Concurrencia competitiva - canónica",
  "presupuestoTotal": 500000,
  "mrr": false,
  "descripcion": "CONVOCATORIA DE AYUDAS A ASTURIANOS Y ASTURIANAS Y DESCENDIENTES RESIDENTES EN EL EXTERIOR. AÑO 2026",
  "descripcionLeng": null,
  "tiposBeneficiarios": [
    {
      "descripcion": "PERSONAS FÍSICAS QUE NO DESARROLLAN ACTIVIDAD ECONÓMICA"
    }
  ],
  "sectores": [
    {
      "descripcion": "ACTIVIDADES SANITARIAS Y DE SERVICIOS SOCIALES",
      "codigo": "R"
    }
  ],
  "regiones": [
    {
      "descripcion": "XXX - Regiones o países no europeos, no contemplados en NUTS"
    }
  ],
  "descripcionFinalidad": "Servicios Sociales y Promoción Social",
  "descripcionBasesReguladoras": "Resolución de 19 de julio de 2019, de la Consejería de Presidencia y Participación Ciudadana, por la que se aprueban las bases reguladoras de la concesión de ayudas individuales para asturianos y asturianas y descendientes residentes en el exterior",
  "urlBasesReguladoras": "https://sede.asturias.es/bopa/2019/08/12/2019-08241.pdf",
  "sePublicaDiarioOficial": true,
  "abierto": false,
  "fechaInicioSolicitud": null,
  "fechaFinSolicitud": null,
  "textInicio": "Día siguiente a publicación de extrato en BOPA",
  "textFin": "30 días hábiles desde el siguiente a publicación",
  "ayudaEstado": null,
  "urlAyudaEstado": null,
  "fondos": [],
  "reglamento": null,
  "objetivos": [],
  "sectoresProductos": [],
  "documentos": [
    {
      "id": 1447606,
      "descripcion": "SOLICITUD",
      "nombreFic": "SOLICITUD.pdf",
      "long": 298297,
      "datMod": "2026-05-04",
      "datPublicacion": "2026-05-04"
    },
    {
      "id": 1447605,
      "descripcion": "Texto en castellano de la convocatoria",
      "nombreFic": "RESOLUCIÓN CONVOCATORIA 2026.pdf",
      "long": 325283,
      "datMod": "2026-05-04",
      "datPublicacion": "2026-05-04"
    }
  ],
  "anuncios": [],
  "advertencia": "La reutilización de los datos del Sistema Nacional de Publicidad de Subvenciones y Ayudas Públicas está sujeta a una serie de restricciones y consideraciones legales. Consulte el aviso legal en https://www.infosubvenciones.es/bdnstrans/GE/es/avisolegal.Además, el usuario debe ser consciente que la información presentada es de naturaleza dinámica, y que los datos pueden ser sometidos a correcciones, inserciones, modificaciones y eliminaciones en momentos posteriores a su extracción. Accesos al API del sistema Nacional de Publicidad de Subvenciones y Ayudas Públicas. La Administración Presupuestaria, para salvaguardar la protección del acceso libre e irrestricto de los ciudadanos a este Portal y a su información podrá adoptar medidas restrictivas de acceso al API ante situaciones de manifiesto abuso del servicio, riesgos de seguridad, o uso fraudulento de la información descargada, de acuerdo con las buenas prácticas de gestión de datos abiertos (https://datos.gob.es/es/blog/limitaciones-la-consulta-de-una-api) establecidas por el Ministerio para la Transformación Digital y de la Función Pública."
}