{
  "source": "bdns",
  "source_id": "903506",
  "source_lang": "es",
  "level": "local",
  "programme": "Concurrencia competitiva - canónica",
  "sub_programme": null,
  "publishing_authority_code": "LOCAL / POLINYÀ / AYUNTAMIENTO DE POLINYÀ",
  "nuts_codes": [
    "ES511"
  ],
  "nuts_primary": "ES511",
  "title": "CONVOCATORIA TERCERA EDICIÓN PREMIOS POLINYÀ INNOVA",
  "title_lang": "es",
  "summary": "Comercio, Turismo y Pymes",
  "status": "open",
  "publication_date": "2026-05-05",
  "open_date": "2026-05-15",
  "deadline": "2026-07-15",
  "deadline_model": "single-stage",
  "deadlines_extra": null,
  "budget_total_eur": 18100,
  "budget_per_project_min_eur": null,
  "budget_per_project_max_eur": null,
  "expected_grants": null,
  "cofinancing_pct": null,
  "duration_months": null,
  "audience": "GRAN EMPRESA; PERSONAS FÍSICAS QUE NO DESARROLLAN ACTIVIDAD ECONÓMICA; PYME Y PERSONAS FÍSICAS QUE DESARROLLAN ACTIVIDAD ECONÓMICA",
  "eligible_orgs": [
    "GRAN EMPRESA",
    "PERSONAS FÍSICAS QUE NO DESARROLLAN ACTIVIDAD ECONÓMICA",
    "PYME Y PERSONAS FÍSICAS QUE DESARROLLAN ACTIVIDAD ECONÓMICA"
  ],
  "eligible_countries": [
    "ES"
  ],
  "sectores": [
    {
      "codigo": "S",
      "descripcion": "ACTIVIDADES ARTÍSTICAS, DEPORTIVAS Y DE ENTRETENIMIENTO"
    }
  ],
  "apply_url": null,
  "details_url": "https://www.infosubvenciones.es/bdnstrans/GE/es/convocatoria/903506",
  "documents": [
    {
      "label": "Texto en otra lengua de la convocatoria",
      "url": null
    },
    {
      "label": "Texto en castellano de la convocatoria",
      "url": null
    }
  ],
  "bases_reguladoras_url": "https://bop.diba.cat/anunci/3605422/aprovacio-inicial-de-les-bases-reguladores-dels-premis-polinya-innova-versio-en-catala-i-castella-ajuntament-de-polinya",
  "text_inicio": null,
  "text_fin": null,
  "se_publica_diario_oficial": true,
  "ayuda_estado": null,
  "fondos": [],
  "reglamento": null,
  "objetivos": [],
  "sectores_productos": [],
  "anuncios": [],
  "mrr_flag": false,
  "fetchedAt": "2026-05-07T12:06:49.172Z"
}