{
  "identifier": "SOCPL-2023-SOC-DIALOG",
  "ccm2Id": "45886553",
  "callIdentifier": "SOCPL-2023-SOC-DIALOG",
  "callTitle": "",
  "title": "Support for social dialogue",
  "programme": "EaSI / SOCPL",
  "programmeCode": "43252517",
  "programmePeriod": "2021 - 2027",
  "status": "open",
  "statusCode": "31094502",
  "opening": "2023-03-29",
  "deadline": "2023-06-28",
  "deadlineModel": "single-stage",
  "actionType": "SOCPL Project Grants",
  "actionCode": null,
  "mgaCode": null,
  "budget": null,
  "keywords": [
    "[]"
  ],
  "crossCuttingPriorities": [],
  "supportInfoText": "",
  "submissionUrl": null,
  "topicUrl": "https://ec.europa.eu/info/funding-tenders/opportunities/data/topicDetails/SOCPL-2023-SOC-DIALOG.json",
  "documents": [],
  "fetchedAt": "2026-07-12T04:05:22.576Z"
}