{
  "id": 1099561,
  "organo": {
    "nivel1": "LOCAL",
    "nivel2": "CANTALLOPS",
    "nivel3": "AYUNTAMIENTO DE CANTALLOPS"
  },
  "sedeElectronica": "https://seu-e.cat/ca/web/cantallops/tramits-i-gestions ",
  "codigoBDNS": "898000",
  "fechaRecepcion": "2026-04-10",
  "instrumentos": [
    {
      "descripcion": "SUBVENCIÓN Y ENTREGA DINERARIA SIN CONTRAPRESTACIÓN "
    }
  ],
  "tipoConvocatoria": "Concurrencia competitiva - canónica",
  "presupuestoTotal": 4000,
  "mrr": false,
  "descripcion": "Convocatoria de subvenciones para el material escolar curso 2025-2026",
  "descripcionLeng": "Convocatòria de subvencions per al material escolar curs 2025-2026",
  "tiposBeneficiarios": [
    {
      "descripcion": "PERSONAS FÍSICAS QUE NO DESARROLLAN ACTIVIDAD ECONÓMICA"
    }
  ],
  "sectores": [
    {
      "descripcion": "ACTIVIDADES ARTÍSTICAS, DEPORTIVAS Y DE ENTRETENIMIENTO",
      "codigo": "S"
    },
    {
      "descripcion": "EDUCACIÓN",
      "codigo": "Q"
    }
  ],
  "regiones": [
    {
      "descripcion": "ES512 - Girona"
    }
  ],
  "descripcionFinalidad": "Educación",
  "descripcionBasesReguladoras": "ORDENANZA GENERAL DE SUBVENCIONES DE CANTALLOPS",
  "urlBasesReguladoras": "https://cantallops.cat/lajuntament/ordenances/",
  "sePublicaDiarioOficial": true,
  "abierto": false,
  "fechaInicioSolicitud": null,
  "fechaFinSolicitud": null,
  "textInicio": "AL DIA SIGUIENTE DE LA PUBLICACION EN EL BOLETIN OFICIAL DE LA PROVINCIA DE GIRONA",
  "textFin": "20 DIAS HABILES A CONTAR DIA SIGUIENTEN DE LA PUBLICACION EN EL BOPG",
  "ayudaEstado": null,
  "urlAyudaEstado": null,
  "fondos": [],
  "reglamento": null,
  "objetivos": [],
  "sectoresProductos": [],
  "documentos": [
    {
      "id": 1432616,
      "descripcion": "Documento de la convocatoria en lengua cooficial",
      "nombreFic": "convocatoria en catala.pdf",
      "long": 400715,
      "datMod": "2026-04-10",
      "datPublicacion": "2026-04-14"
    },
    {
      "id": 1432615,
      "descripcion": "Documento de la convocatoria en español",
      "nombreFic": "convocatoria en castella.pdf",
      "long": 189067,
      "datMod": "2026-04-10",
      "datPublicacion": "2026-04-14"
    }
  ],
  "anuncios": [
    {
      "numAnuncio": 208432,
      "titulo": "convocatoria de subvenciones para el material escolar curso 2025-2026",
      "tituloLeng": "Convocatòria de subvencions per al material escolar curs 2025-2026",
      "texto": "<p>1. BASES REGULADORAS</p><p>Las subvenciones convocadas se regirán por las Bases Generales de subvenciones el Ayuntamiento de Cantallops publicadas en el Boletín Oficial de la Provincia de Girona Nº. 196 · Nº. edicto 9112 · Fecha 14-10-2025.</p><p>2. CUANTÍA Y CRÉDITO PRESUPUESTARIO</p><p>Las subvenciones se concederán con cargo a la partida presupuestaria 3260-48000 SUBVENCION ESCOLAR, con el límite de 4.000 euros.</p><p>3. OBJETO, CONDICIONES Y FINALIDAD</p><p>La presente convocatoria tiene por objeto la subvención del material escolar curso 2025-2026, de conformidad con lo previsto en las correspondientes bases reguladoras, que reúnan las siguientes condiciones:</p><p>- adquisición de libros de texto para el curso escolar 2025/2026</p><p>- material escolar 2025/2026</p><p>El importe máximo individualizado de la ayuda, por cada alumno/a, será de 100,00 euros. En ningún caso el importe de la ayuda otorgada podrá ser superior al gasto justificado.</p><p>Habrá que justificar que ninguno de los gastos realizados en libros o material escolar para el curso 2025/2026, que son objeto de esta subvención, ha sido cubierta mediante los “vales de ayuda” que la Generalidad de Cataluña ha enviado este curso 2025/2026 a los alumnos de primaria y secundaria.</p><p>Una forma de justificarlo es acreditar gastos en libros y/o material escolar del curso 2025/2026 que superen los 60 euros de los \"vales\" escolares de la Generalitat.</p><p>La concesión de las ayudas contempladas en la presente convocatoria se sujetará a los principios de publicidad, transparencia, concurrencia, objetividad, igualdad y no discriminación, así como su eficacia en el cumplimiento de objetivos y eficiencia en la asignación y utilización de los recursos públicos.</p><p>4. RÉGIMEN DE OTORGAMIENTO</p><p>La subvención objeto de la presente convocatoria se otorgará en régimen de concurrencia competitiva, mediante la comparación y puntuación de las solicitudes presentadas al efecto por los interesados.</p><p>5. REQUISITOS PARA SOLICITAR LA SUBVENCIÓN Y FORMA DE ACREDITARLOS</p><p>Podrán solicitar las subvenciones objeto de esta convocatoria, los interesados &#8203;&#8203;descritos en la Base tercera de las Bases reguladoras, que cumplan los siguientes requisitos:</p><p>- El alumno y al menos uno de los padres deben estar empadronados en el municipio de Cantallops en el momento de realizar la solicitud.</p><p>- Ser alumnos de educación primaria o secundaria, es decir, de 1º de primaria hasta 4º de ESO, en cualquier centro educativo o Instituto.</p><p>- Presentar la solicitud en el plazo y forma establecido.</p><p>- El solicitante ni ningún integrante de la unidad familiar y/o convivencia podrán tener deudas pendientes de pago con la Hacienda municipal, salvo que éstas tengan concedido por el Ayuntamiento el aplazamiento o el fraccionamiento.</p><p>- Podrán solicitar estas ayudas los padres, madres, tutores legales o personas encargadas temporal o definitivamente de la guarda de los alumnos beneficiarias menores de edad, o los alumnos mayores de edad, siempre que se cumplan los siguientes requisitos:</p><p>- Cumplir con las condiciones socioeconómicas establecidas en las bases.</p><p>- No haber obtenido otras ayudas, becas o aportaciones de otras administraciones públicas o entidades por el mismo concepto.</p><p>- Presentar la documentación requerida para acreditar la relación familiar y de convivencia y la situación socioeconómica y académica.</p><p>Los requisitos mencionados se acreditarán mediante alguno de los documentos que a continuación se indican:</p><p>- Las solicitudes deben formalizarse de conformidad con el modelo de instancia normalizado que el Ayuntamiento de Cantallops facilitará a las personas interesadas, y que también podrá encontrar en este apartado.</p><p>- Si la ayuda se solicita para más de un hijo/a, será necesario presentar un impreso por cada uno.</p><p>Documentación que debe acompañar la solicitud de subvención</p><p>Las solicitudes deben estar firmadas por cualquiera de los representantes legales del beneficiario menor o por los solicitantes mayores de edad y deben presentarse acompañadas de la siguiente documentación:</p><p>- Instancia firmada, que consta de declaración jurada y responsable.</p><p>- DNI, NIE, Pasaporte, Libro de familia.</p><p>- Hoja de matrícula del centro escolar púb lico o concertado correspondiente u otro documento acreditativo.</p><p>- Facturas o justificantes de gasto de compra de los libros de texto y/o material escolar, en los que conste de forma detallada los artículos de los que se solicita la ayuda económica, así como el impreso del Centro Educativo donde consta la relación de los libros y material escolar a comprar por el curso correspondiente o documento análogo.</p><p>(Si presenta la solicitud telemáticamente, deberá aportar los originales de la documentación escaneada – en las oficinas del ayuntamiento– para poder compulsar/comprobar las copias escaneadas).</p><p>6. ÓRGANOS COMPETENTES</p><p>A efectos de la instrucción y ordenación del expediente de subvención, será el servicio de secretaría el órgano competente.</p><p>La competencia para resolver el expediente corresponde al Alcalde por delegación del Pleno de la Corporación adoptado en sesión ordinaria de fecha 8 de julio de 2025</p><p>7. PLAZO DE PRESENTACIÓN DE SOLICITUDES Y DOCUMENTACIÓN</p><p>Las solicitudes se pueden presentar:</p><p>De forma telemática en el registro electrónico del Ayuntamiento, https://cantallops.cat/ en el apartado trámites y gestiones, instancia genérica: https://seu-e.cat/ca/web/cantallops/tramits-i-gestions/-/tramits/tramit/12344004?p_auth=1Tcrj </p><p>Presencialmente en las oficinas del Ayuntamiento de Cantallops, en horario de atención al público.</p><p>El plazo de presentación será de 20 días hábiles a contar desde el siguiente a la publicación del extracto de la convocatoria en el Boletín Oficial de la Provincia de Girona.</p><p>Asimismo, también podrán presentarse en cualquiera de los lugares establecidos en el artículo 16.4 de la Ley 39/2015, de 1 de octubre, de Procedimiento Administrativo Común de las Administraciones Públicas.</p><p>8. PLAZO DE RESOLUCIÓN Y NOTIFICACIÓN</p><p>Una vez valoradas y comprobadas las solicitudes presentadas, se remitirá propuesta de resolución del procedimiento al órgano competente para su concesión.</p><p>El Ayuntamiento de Cantallops tiene la potestad de requerir la presentación de documentación complementaria imprescindible para efectuar una correcta valoración de la solicitud.</p><p>Las resoluciones se notificarán de forma individualizada a las familias solicitantes.</p><p>El plazo de resolución y notificación será de seis meses</p><p>El vencimiento del plazo máximo sin haberse notificado la resolución legitima a los interesados &#8203;&#8203;para entender desestimada por silencio administrativo la solicitud de concesión de la subvención.</p><p>9. CRITERIOS DE VALORACIÓN DE SOLICITUDES</p><p>El importe máximo individualizado de la ayuda, por cada alumno/a, será de 100,00 euros.</p><p>En ningún caso el importe de la ayuda otorgada podrá ser superior al gasto justificado.</p><p>Se concederán las ayudas a todas las solicitudes que reúnan los requisitos establecidos en esta ordenanza, siempre y cuando exista disponibilidad presupuestaria.</p><p>En caso de que las ayudas solicitadas superen la consignación presupuestaria asignada, ésta se prorrateará entre los peticionarios.</p><p>10. MEDIOS DE NOTIFICACIÓN O PUBLICACIÓN</p><p>Las notificaciones se practicarán en el lugar y por el medio que el solicitante haga constar al efecto en la solicitud, teniendo en cuenta lo fijado a estos efectos en el artículo 41 de la Ley 39/2015, de 1 de octubre, del Procedimiento Administrativo Común de las Administraciones Públicas.</p><p>11. RECURSOS</p><p>La resolución del procedimiento pone fin a la vía administrativa y contra ésta puede interponerse recurso contencioso administrativo en el plazo de dos meses a contar desde el día siguiente a su notificación.</p><p>Alternativamente y de forma potestativa, se puede interponer recurso de reposición ante el Alcalde del Ayuntamiento en el plazo de un mes a contar desde el día siguiente a su notificación.</p><p> </p><p> </p>",
      "textoLeng": "<p>1. BASES REGULADORES </p><p>Les subvencions convocades es regiran per les Bases Generals de subvencions l'Ajuntament de Cantallops publicades al Butlletí Oficial de la Província de Girona Núm. 196 · Núm. edicte 9112 · Data 14-10-2025.  2. QUANTIA I CRÈDIT PRESSUPOSTARI Les subvencions es concediran amb càrrec a la partida pressupostària 3260-48000 SUBVENCIO ESCOLAR, amb el límit de 4.000 euros. </p><p>3. OBJECTE, CONDICIONS I FINALITAT </p><p>La present convocatòria té per objecte la subvenció del material escolar curs 2025-2026, de conformitat amb allò previst a les corresponents bases reguladores, que reuneixin les següents condicions: </p><p>•    adquisició de llibres de text per al curs escolar 2025/2026•    material escolar 2025/2026</p><p>L’import màxim individualitzat de l’ajut, per cada alumne/a, serà de 100,00 euros. En cap cas l’import de l’ajut atorgat podrà ser superior a la despesa justificada.</p><p>Caldrà justificar que cap de les despeses realitzades en llibres o material escolar per al curs 2025/2026, que són objecte d’aquesta subvenció, ha estat coberta mitjançant els “vals d’ajut” que la Generalitat de Catalunya ha enviat aquest curs 2025/2026 als alumnes de primària i secundària.</p><p>Una forma de justificar-ho és acreditar despeses en llibres i/o material escolar del curs 2025/2026 que superin els 60 euros dels “vals” escolars de la Generalitat. </p><p>La concessió de les ajudes contemplades en la present convocatòria se subjectarà als principis de publicitat, transparència, concurrència, objectivitat, igualtat i no discriminació, així com l'eficàcia en el compliment d'objectius i eficiència en l'assignació i utilització dels recursos públics.</p><p>4. RÈGIM D'ATORGAMENT </p><p>La subvenció objecte de la present convocatòria s'atorgarà en règim de concurrència competitiva, mitjançant la comparació i puntuació de les sol·licituds presentades a l'efecte pels interessats. </p><p>5. REQUISITS PER SOL·LICITAR LA SUBVENCIÓ I FORMA D'ACREDITAR-LOS </p><p>Podran sol·licitar les subvencions objecte d'aquesta convocatòria, els interessats descrits en la Base tercera de les Bases reguladores, que compleixin els següents requisits: •    L’alumne i almenys un dels pares han d’estar empadronats al municipi de Cantallops en el moment de realitzar la sol·licitud. •    Ser alumnes d’educació primària o secundària, és a dir, de 1r de primària fins a 4t d’ESO, en qualsevol centre educatiu o Institut.•    Presentar la sol·licitud en el termini i forma establert.•    El sol·licitant ni cap integrant de la unitat familiar i/o convivència no podran tenir deutes pendents de pagament amb la Hisenda municipal, llevat que aquests tinguin concedit per l’Ajuntament l’ajornament o el fraccionament.Podran sol·licitar aquests ajuts els pares, les mares, els tutors legals o les persones encarregades temporalment o definitivament de la guarda dels alumnes beneficiàries menors d’edat, o els alumnes majors d’edat, sempre que es compleixin els requisits següents:•    Complir amb les condicions socioeconòmiques establertes a les bases.•    No haver obtingut altres ajuts, beques o aportacions d’altres administracions públiques o entitats per al mateix concepte.•    Presentar la documentació requerida per acreditar la relació familiar i de convivència, i la situació socioeconòmica i acadèmica.Els requisits esmentats s'acreditaran mitjançant algun dels documents que a continuació s'indiquen: </p><p>Les sol·licituds s’han de formalitzar de conformitat amb el model d’instància normalitzat que l’Ajuntament de Cantallops facilitarà a les persones interessades, i que també podreu trobar en aquest apartat.</p><p>Si l’ajut se sol·licita per a més d’un fill/a, caldrà presentar un imprès per cadascun.</p><p>Documentació que ha d’acompanyar la sol·licitud de subvencióLes sol·licituds han d’estar signades per qualsevol dels representants legals del beneficiari menor o pels sol·licitants majors d’edat i s’han de presentar acompanyades de la documentació següent:</p><p>•    Instància signada, que consta de declaració jurada i responsable.•    DNI, NIE, Passaport, Llibre de família.•    Full de matrícula del centre escolar públic o concertat corresponent o altre document acreditatiu.•     Factures o justificants de despesa de compra del llibres de text i/o material escolar, on consti de forma detallada els articles dels que es sol·licita l’ajut econòmic, així com l’imprès del Centre Educatiu on consta la relació dels llibres i material escolar a comprar pel curs corresponent o document anàleg.</p><p>(Si presenteu la sol·licitud telemàticament, caldrà que aporteu els originals de la documentació escanejada – a les oficines de l’ajuntament– per tal de poder compulsar/comprovar les còpies escanejades).  6. ÒRGANS COMPETENTS </p><p>A l'efecte de la instrucció i ordenació de l'expedient de subvenció, serà el servei de secretaria l’òrgan competent. </p><p>La competència per resoldre l'expedient correspon a l’Alcalde per delegació del Ple de la Corporació adoptat en sessió ordinària de data 8 de juliol de 2025. </p><p>7. TERMINI DE PRESENTACIÓ DE SOL·LICITUDS I DOCUMENTACIÓ </p><p>Les sol·licituds es poden presentar:</p><p>•    De forma telemàtica en el registre electrònic de l’Ajuntament, https://cantallops.cat/ en l’apartat tràmits i gestions, instància genèrica: https://seu-e.cat/ca/web/cantallops/tramits-i-gestions/-/tramits/tramit/12344004?p_auth=1TcrjzhI </p><p>•    Presencialment en les oficines de l‘Ajuntament de Cantallops, en horari d’atenció al públic.</p><p>El termini de presentació serà de 20 dies hàbils a comptar des del dia següent a la publicació de l’extracte de la convocatòria en el Butlletí Oficial de la Província de Girona.</p><p>Així mateix també podran presentar-se en qualsevol dels llocs establerts en l’article 16.4 de la Llei 39/2015, d’1 d’octubre, de Procediment Administratiu Comú de les Administracions Públiques.</p><p>8. TERMINI DE RESOLUCIÓ I NOTIFICACIÓ </p><p>Una vegada valorades i comprovades les sol·licituds presentades es remetrà proposta de resolució del procediment a l’òrgan competent per a la seva concessió.</p><p>L’Ajuntament de Cantallops té la potestat de requerir la presentació de documentaciócomplementària imprescindible per efectuar una correcta valoració de la sol·licitud.</p><p>Les resolucions es notificaran de forma individualitzada a les famílies sol·licitants.</p><p>El termini de resolució i notificació serà de sis mesos</p><p>El venciment del termini màxim sense haver-se notificat la resolució legitima als interessats per entendre desestimada per silenci administratiu la sol·licitud de concessió de la subvenció.  </p><p>9. CRITERIS DE VALORACIÓ DE SOL·LICITUDSL’import màxim individualitzat de l’ajut, per cada alumne/a, serà de 100,00 euros.</p><p>En cap cas l’import de l’ajut atorgat podrà ser superior a la despesa justificada.</p><p>Es concediran els ajuts a totes les sol·licituds que reuneixin els requisits establerts en aquesta ordenança, sempre i quan hi hagi disponibilitat pressupostària.</p><p>En el cas que els ajuts sol·licitats superin la consignació pressupostària assignada, aquesta es prorratejarà entre els peticionaris.</p><p>10. MITJANS DE NOTIFICACIÓ O PUBLICACIÓ</p><p>Les notificacions es practicaran en el lloc i pel mitjà que el sol·licitant faci constar a aquest efecte en la sol·licitud, tenint en compte allò que s'ha fixat a aquests efectes en l'article 41 de la Llei 39/2015, d'1 d'octubre, del Procediment Administratiu Comú de les Administracions Públiques.</p><p> </p>",
      "url": "https://ssl4.ddgi.cat/bopV1/pdf/2026/74/20267403079.pdf",
      "cve": null,
      "desDiarioOficial": "B.O.P. DE GIRONA",
      "datPublicacion": "2026-04-20"
    }
  ],
  "advertencia": "La reutilización de los datos del Sistema Nacional de Publicidad de Subvenciones y Ayudas Públicas está sujeta a una serie de restricciones y consideraciones legales. Consulte el aviso legal en https://www.infosubvenciones.es/bdnstrans/GE/es/avisolegal.Además, el usuario debe ser consciente que la información presentada es de naturaleza dinámica, y que los datos pueden ser sometidos a correcciones, inserciones, modificaciones y eliminaciones en momentos posteriores a su extracción. Accesos al API del sistema Nacional de Publicidad de Subvenciones y Ayudas Públicas. La Administración Presupuestaria, para salvaguardar la protección del acceso libre e irrestricto de los ciudadanos a este Portal y a su información podrá adoptar medidas restrictivas de acceso al API ante situaciones de manifiesto abuso del servicio, riesgos de seguridad, o uso fraudulento de la información descargada, de acuerdo con las buenas prácticas de gestión de datos abiertos (https://datos.gob.es/es/blog/limitaciones-la-consulta-de-una-api) establecidas por el Ministerio para la Transformación Digital y de la Función Pública."
}