{"id":1105866,"organo":{"nivel1":"LOCAL","nivel2":"DIPUTACIÓN PROV. DE TARRAGONA","nivel3":"DIPUTACIÓN PROVINCIAL DE TARRAGONA"},"sedeElectronica":"https://seuelectronica.dipta.cat","codigoBDNS":"904305","fechaRecepcion":"2026-05-08","instrumentos":[{"descripcion":"SUBVENCIÓN Y ENTREGA DINERARIA SIN CONTRAPRESTACIÓN "}],"tipoConvocatoria":"Concurrencia competitiva - canónica","presupuestoTotal":112000,"mrr":false,"descripcion":"Museos registrados entidades locales y personas jurídicas privadas. Actividades 2026","descripcionLeng":"Museus registrats ens locals i entitats. Activitat","tiposBeneficiarios":[{"descripcion":"PERSONAS JURÍDICAS QUE NO DESARROLLAN ACTIVIDAD ECONÓMICA"}],"sectores":[{"descripcion":"Actividades de bibliotecas, archivos, museos y otras actividades culturales","codigo":"91"}],"regiones":[{"descripcion":"ES51 - CATALUÑA"}],"descripcionFinalidad":"Cultura","descripcionBasesReguladoras":"Bases generales de subvenciones de la Diputació de Tarragona y de sus Organismos Autónomos","urlBasesReguladoras":"https://www.diputaciodetarragona.cat/ebop/index.php?op=anunci&id=1723&ebop_any=2019","sePublicaDiarioOficial":true,"abierto":false,"fechaInicioSolicitud":null,"fechaFinSolicitud":null,"textInicio":"Dia siguiente a la publicación de la convocatoria en el BOPT.","textFin":"Un mes desde la fecha de publicación en el BOPT. ","ayudaEstado":null,"urlAyudaEstado":null,"fondos":[],"reglamento":null,"objetivos":[],"sectoresProductos":[],"documentos":[{"id":1450850,"descripcion":"Texto en otra lengua de la convocatoria","nombreFic":"CONVOCATÒRIA MUSEUS CAT 2026.PDF","long":407961,"datMod":"2026-05-08","datPublicacion":"2026-05-08"},{"id":1450849,"descripcion":"Texto en castellano de la convocatoria","nombreFic":"CONVOCATÒRIA MUSEUS 2026- CASTELLÀ.PDF","long":307705,"datMod":"2026-05-08","datPublicacion":"2026-05-08"}],"anuncios":[],"advertencia":"La reutilización de los datos del Sistema Nacional de Publicidad de Subvenciones y Ayudas Públicas está sujeta a una serie de restricciones y consideraciones legales. Consulte el aviso legal en https://www.infosubvenciones.es/bdnstrans/GE/es/avisolegal.Además, el usuario debe ser consciente que la información presentada es de naturaleza dinámica, y que los datos pueden ser sometidos a correcciones, inserciones, modificaciones y eliminaciones en momentos posteriores a su extracción. Accesos al API del sistema Nacional de Publicidad de Subvenciones y Ayudas Públicas. La Administración Presupuestaria, para salvaguardar la protección del acceso libre e irrestricto de los ciudadanos a este Portal y a su información podrá adoptar medidas restrictivas de acceso al API ante situaciones de manifiesto abuso del servicio, riesgos de seguridad, o uso fraudulento de la información descargada, de acuerdo con las buenas prácticas de gestión de datos abiertos (https://datos.gob.es/es/blog/limitaciones-la-consulta-de-una-api) establecidas por el Ministerio para la Transformación Digital y de la Función Pública."}